flowdock.py
influx
setup.py
python_flowdock.egg-info/PKG-INFO
python_flowdock.egg-info/SOURCES.txt
python_flowdock.egg-info/dependency_links.txt
python_flowdock.egg-info/requires.txt
python_flowdock.egg-info/top_level.txt