Metadata-Version: 1.0
Name: python-flowdock
Version: 0.1
Summary: Python client for FlowDock API
Home-page: UNKNOWN
Author: Joshua Ginsberg
Author-email: jag@flowtheory.net
License: LGPLv3
Keywords: flowdock api
Platform: UNKNOWN
Classifier: Development Status :: 4 - Beta
Classifier: Environment :: Console
Classifier: Intended Audience :: Developers
Classifier: License :: OSI Approved :: GNU Library or Lesser General Public License (LGPL)
Classifier: Topic :: Communications
